SpyDust/AngMomDist.py
SpyDust/Grain.py
SpyDust/H2_photoemission.py
SpyDust/SED.py
SpyDust/SED_fit.py
SpyDust/SpyDust.py
SpyDust/__init__.py
SpyDust/charge_dist.py
SpyDust/collisions.py
SpyDust/free_free.py
SpyDust/full_Stokes.py
SpyDust/infrared.py
SpyDust/mom_exp.py
SpyDust/mpiutil.py
SpyDust/plasmadrag.py
SpyDust/util.py
SpyDust/Data_Files/FIR_integral_charged_30a_30chi.txt
SpyDust/Data_Files/FIR_integral_neutral_30a_30chi.txt
SpyDust/Data_Files/GIR_integral_charged_30a_30chi.txt
SpyDust/Data_Files/GIR_integral_neutral_30a_30chi.txt
SpyDust/Data_Files/PAHion_read.out
SpyDust/Data_Files/PAHneu_read.out
SpyDust/Data_Files/Tev_30a_30chi.txt
SpyDust/Data_Files/gff.dat
SpyDust/Data_Files/gp_neg_110psi_150Omega.txt
SpyDust/Data_Files/gp_neutral_300phi_150Omega.txt
SpyDust/Data_Files/gp_pos_110psi_150Omega.txt
SpyDust/Data_Files/int_plasma.npz
SpyDust/Data_Files/jpeisrf_data.npz
SpyDust/Data_Files/parallel.out
SpyDust/Data_Files/perpendicular.out
SpyDust/Data_Files/sizedists_table1.out
SpyDust/SPDUST_as_is/H2_photoemission.py
SpyDust/SPDUST_as_is/__init__.py
SpyDust/SPDUST_as_is/charge_dist.py
SpyDust/SPDUST_as_is/collisions.py
SpyDust/SPDUST_as_is/emissivity.py
SpyDust/SPDUST_as_is/grain_properties.py
SpyDust/SPDUST_as_is/infrared.py
SpyDust/SPDUST_as_is/plasmadrag.py
SpyDust/SPDUST_as_is/spdust.py
spydust-1.3.dist-info/METADATA
spydust-1.3.dist-info/WHEEL
spydust-1.3.dist-info/top_level.txt
spydust-1.3.dist-info/RECORD
