Metadata-Version: 2.4
Name: SpyDust
Version: 1.3
Summary: A code for modeling spinning dust radiation
Home-page: https://github.com/zzhang0123/SpyDust
Author: Zheng Zhang
Author-email: Zheng Zhang <zheng.zhang@manchester.ac.uk>
Project-URL: Homepage, https://github.com/zzhang0123/SpyDust
Keywords: astrophysics,astronomy
Classifier: Development Status :: 5 - Production/Stable
Classifier: License :: OSI Approved :: MIT License
Classifier: Programming Language :: Python :: 3
Requires-Python: >=3.7, <4
Requires-Dist: numpy<2.4
Requires-Dist: scipy
Requires-Dist: mpi4py
Dynamic: author
Dynamic: home-page
Dynamic: requires-python
